oarepo_rdm/__init__.py
oarepo_rdm/errors.py
oarepo_rdm/ext.py
oarepo_rdm/invenio_ext.py
oarepo_rdm/proxies.py
oarepo_rdm/oai/__init__.py
oarepo_rdm/oai/config.py
oarepo_rdm/oai/percolator.py
oarepo_rdm/oai/record.py
oarepo_rdm/oai/serializer.py
oarepo_rdm/records/__init__.py
oarepo_rdm/records/systemfields/__init__.py
oarepo_rdm/records/systemfields/pid.py
oarepo_rdm/resources/__init__.py
oarepo_rdm/resources/records/__init__.py
oarepo_rdm/resources/records/config.py
oarepo_rdm/services/__init__.py
oarepo_rdm/services/config.py
oarepo_rdm/services/service.py
tests/__init__.py
tests/conftest.py
tests/handlers.py
tests/test_oai.py
tests/test_pid.py
tests/test_resources.py
tests/test_search.py
tests/test_search_drafts.py
tests/test_secret_links.py
tests/test_service.py
tests/test_service_tasks.py
tests/ui/__init__.py
tests/ui/common.py
tests/ui/modela.py
tests/ui/modelb.py
tests/ui/modelc.py
oarepo_rdm-0.6.1.dist-info/METADATA
oarepo_rdm-0.6.1.dist-info/WHEEL
oarepo_rdm-0.6.1.dist-info/entry_points.txt
oarepo_rdm-0.6.1.dist-info/top_level.txt
oarepo_rdm-0.6.1.dist-info/RECORD
