Metadata-Version: 2.4
Name: oarepo-rdm
Version: 0.6.1
Requires-Dist: oarepo-global-search
Provides-Extra: dev
Requires-Dist: pytest>=7.1.2; extra == "dev"
Requires-Dist: pytest-oarepo; extra == "dev"
Requires-Dist: black; extra == "dev"
Requires-Dist: isort; extra == "dev"
Requires-Dist: autoflake; extra == "dev"
Requires-Dist: oarepo-tools; extra == "dev"
Provides-Extra: tests
Requires-Dist: pytest>=7.1.2; extra == "tests"
Requires-Dist: pytest-oarepo; extra == "tests"
